{"version":1,"addons":{"gmp-widevinecdm":{"id":"gmp-widevinecdm","enabled":true,"installed":true,"modified":1781636803370,"type":"plugin","scope":4,"foreignInstall":false},"gmp-widevinecdm-l1":{"id":"gmp-widevinecdm-l1","enabled":true,"installed":false,"modified":1781636791098,"type":"plugin","scope":4,"foreignInstall":false},"firefox-compact-dark@mozilla.org":{"id":"firefox-compact-dark@mozilla.org","guid":"{ef19901d-db26-4cee-827c-d6ede36111fc}","enabled":true,"installed":true,"modified":1781636791108,"type":"theme","scope":4,"foreignInstall":false,"isSyncable":false},"default-theme@mozilla.org":{"id":"default-theme@mozilla.org","guid":"{0f4956e0-c188-4564-90fd-9cad5dcf127c}","enabled":false,"installed":true,"modified":1781636791109,"type":"theme","scope":4,"foreignInstall":false,"isSyncable":false},"data-leak-blocker@mozilla.com":{"id":"data-leak-blocker@mozilla.com","guid":"{b672d716-589a-47e1-977c-304101c71cce}","enabled":true,"installed":true,"modified":1781636794015,"type":"extension","scope":4,"foreignInstall":false,"isSyncable":false},"formautofill@mozilla.org":{"id":"formautofill@mozilla.org","guid":"{3eabc9fe-2037-4380-9175-268dc89b712e}","enabled":true,"installed":true,"modified":1781636794016,"type":"extension","scope":4,"foreignInstall":false,"isSyncable":false},"ipp-activator@mozilla.com":{"id":"ipp-activator@mozilla.com","guid":"{0ae13a73-ff08-4e9c-b711-bdd746b045b3}","enabled":true,"installed":true,"modified":1781636794016,"type":"extension","scope":4,"foreignInstall":false,"isSyncable":false},"newtab@mozilla.org":{"id":"newtab@mozilla.org","guid":"{3dd67612-f764-44a5-a820-06d585da9a23}","enabled":true,"installed":true,"modified":1781636794016,"type":"extension","scope":4,"foreignInstall":false,"isSyncable":true},"pictureinpicture@mozilla.org":{"id":"pictureinpicture@mozilla.org","guid":"{936b1a11-1151-4106-b042-a26caa43d5a3}","enabled":true,"installed":true,"modified":1781636794016,"type":"extension","scope":4,"foreignInstall":false,"isSyncable":false},"addons-search-detection@mozilla.com":{"id":"addons-search-detection@mozilla.com","guid":"{1e722264-1a3a-4589-831d-62e47907ea76}","enabled":true,"installed":true,"modified":1781636794016,"type":"extension","scope":4,"foreignInstall":false,"isSyncable":false},"webcompat@mozilla.org":{"id":"webcompat@mozilla.org","guid":"{a38ad8da-4c4d-4185-a4c8-7a331996086c}","enabled":true,"installed":true,"modified":1781636794016,"type":"extension","scope":4,"foreignInstall":false,"isSyncable":false},"firefox-compact-light@mozilla.org":{"id":"firefox-compact-light@mozilla.org","guid":"{2970e544-c850-4b13-a30d-e773203293c3}","enabled":false,"installed":true,"modified":1781636794016,"type":"theme","scope":4,"foreignInstall":false,"isSyncable":false},"firefox-alpenglow@mozilla.org":{"id":"firefox-alpenglow@mozilla.org","guid":"{d8ea3c5c-0e0e-4db3-a04c-b5444acf48d8}","enabled":false,"installed":true,"modified":1781636794016,"type":"theme","scope":4,"foreignInstall":false,"isSyncable":false},"gmp-gmpopenh264":{"id":"gmp-gmpopenh264","enabled":true,"installed":true,"modified":1781636794016,"type":"plugin","scope":4,"foreignInstall":false},"jid1-BoFifL9Vbdl2zQ@jetpack":{"id":"jid1-BoFifL9Vbdl2zQ@jetpack","guid":"{131addfb-28c1-43c2-b0b0-cdc90d3471b1}","enabled":true,"installed":true,"modified":1781636795542,"type":"extension","scope":1,"foreignInstall":false,"isSyncable":true},"{264206b8-8ba0-4824-8eeb-9d8d0520086f}":{"id":"{264206b8-8ba0-4824-8eeb-9d8d0520086f}","guid":"{376c1bb7-3ae3-4ad5-b81e-12015f1e9f11}","enabled":true,"installed":true,"modified":1781636796033,"type":"extension","scope":1,"foreignInstall":false,"isSyncable":true},"uBlock0@raymondhill.net":{"id":"uBlock0@raymondhill.net","guid":"{4b39c03e-3df7-4742-8b61-19f804e9e665}","enabled":true,"installed":true,"modified":1781636796658,"type":"extension","scope":1,"foreignInstall":false,"isSyncable":true},"jid1-MnnxcxisBPnSXQ@jetpack":{"id":"jid1-MnnxcxisBPnSXQ@jetpack","guid":"{568fa90a-f347-480a-8eb6-dc48c1a1f1bd}","enabled":true,"installed":true,"modified":1781636796979,"type":"extension","scope":1,"foreignInstall":false,"isSyncable":true},"chrome-gnome-shell@gnome.org":{"id":"chrome-gnome-shell@gnome.org","guid":"{627e5aad-867f-49ba-9399-7fafae779d94}","enabled":true,"installed":true,"modified":1781636797129,"type":"extension","scope":1,"foreignInstall":false,"isSyncable":true},"{d812469e-821e-4770-8513-e42e9eccfd45}":{"id":"{d812469e-821e-4770-8513-e42e9eccfd45}","guid":"{7ef80813-96c0-4067-98a3-5cd521196794}","enabled":false,"installed":true,"modified":1781636797462,"type":"theme","scope":1,"foreignInstall":false,"isSyncable":true},"{74145f27-f039-47ce-a470-a662b129930a}":{"id":"{74145f27-f039-47ce-a470-a662b129930a}","guid":"{dc3b4998-b28a-40c6-a18e-a743cdc5307a}","enabled":true,"installed":true,"modified":1781636797714,"type":"extension","scope":1,"foreignInstall":false,"isSyncable":true}},"changes":[[1781636791004,1,"gmp-widevinecdm"],[1781636791098,1,"gmp-widevinecdm-l1"],[1781636791108,1,"firefox-compact-dark@mozilla.org"],[1781636791109,1,"default-theme@mozilla.org"],[1781636794015,1,"data-leak-blocker@mozilla.com"],[1781636794016,1,"formautofill@mozilla.org"],[1781636794016,1,"ipp-activator@mozilla.com"],[1781636794016,1,"newtab@mozilla.org"],[1781636794016,1,"pictureinpicture@mozilla.org"],[1781636794016,1,"addons-search-detection@mozilla.com"],[1781636794016,1,"webcompat@mozilla.org"],[1781636794016,1,"firefox-compact-light@mozilla.org"],[1781636794016,1,"firefox-alpenglow@mozilla.org"],[1781636794016,1,"gmp-gmpopenh264"],[1781636794016,2,"gmp-widevinecdm-l1"],[1781636795542,1,"jid1-BoFifL9Vbdl2zQ@jetpack"],[1781636796033,1,"{264206b8-8ba0-4824-8eeb-9d8d0520086f}"],[1781636796658,1,"uBlock0@raymondhill.net"],[1781636796979,1,"jid1-MnnxcxisBPnSXQ@jetpack"],[1781636797129,1,"chrome-gnome-shell@gnome.org"],[1781636797462,1,"{d812469e-821e-4770-8513-e42e9eccfd45}"],[1781636797714,1,"{74145f27-f039-47ce-a470-a662b129930a}"],[1781636803366,2,"gmp-widevinecdm"]]}